baladin/__init__.py
baladin/core.py
baladin-0.0.2.dist-info/LICENSE.txt
baladin-0.0.2.dist-info/METADATA
baladin-0.0.2.dist-info/WHEEL
baladin-0.0.2.dist-info/top_level.txt
baladin-0.0.2.dist-info/RECORD
