Metadata-Version: 2.1
Name: baladin
Version: 0.0.2
Summary: Pythonic tool to work with Aladin Lite
Home-page: https://github.com/behrouzz/baladin
Author: Behrouz Safari
Author-email: behrouz.safari@gmail.com
License: MIT
Classifier: Programming Language :: Python :: 3
Classifier: License :: OSI Approved :: MIT License
Classifier: Operating System :: OS Independent
Requires-Python: >=3.6
License-File: LICENSE.txt
